abductio_core/__init__.py
abductio_core/adapters/__init__.py
abductio_core/adapters/openai_llm.py
abductio_core/application/__init__.py
abductio_core/application/canonical.py
abductio_core/application/dto.py
abductio_core/application/ports.py
abductio_core/application/result.py
abductio_core/application/use_cases/__init__.py
abductio_core/application/use_cases/replay_session.py
abductio_core/application/use_cases/run_session.py
abductio_core/domain/__init__.py
abductio_core/domain/audit.py
abductio_core/domain/canonical.py
abductio_core/domain/invariants.py
abductio_core/domain/model.py
abductio_core-0.2.2.dist-info/licenses/LICENSE
abductio_core-0.2.2.dist-info/METADATA
abductio_core-0.2.2.dist-info/WHEEL
abductio_core-0.2.2.dist-info/entry_points.txt
abductio_core-0.2.2.dist-info/top_level.txt
abductio_core-0.2.2.dist-info/RECORD
