Metadata-Version: 2.4
Name: abductio-core
Version: 0.2.2
Summary: ABDUCTIO MVP core engine
Author-email: David Joseph <david@promise.foundation>
License: MIT
Project-URL: Homepage, https://github.com/Promise-Foundation/abductio-core
Project-URL: Repository, https://github.com/Promise-Foundation/abductio-core
Project-URL: Issues, https://github.com/Promise-Foundation/abductio-core/issues
Keywords: abductio,reasoning,abduction,hypotheses,credence
Classifier: License :: OSI Approved :: MIT License
Classifier: Programming Language :: Python :: 3
Classifier: Programming Language :: Python :: 3 :: Only
Classifier: Programming Language :: Python :: 3.11
Classifier: Programming Language :: Python :: 3.12
Classifier: Typing :: Typed
Requires-Python: >=3.11
License-File: LICENSE
Requires-Dist: openai>=1.0
Requires-Dist: pydantic>=2.7
Provides-Extra: dev
Requires-Dist: behave>=1.2.6; extra == "dev"
Requires-Dist: ruff>=0.6.0; extra == "dev"
Requires-Dist: mypy>=1.10.0; extra == "dev"
Requires-Dist: pytest>=7.0; extra == "dev"
Requires-Dist: coverage>=7.0; extra == "dev"
Provides-Extra: e2e
Requires-Dist: pytest>=7.0; extra == "e2e"
Dynamic: license-file
